music_riff/__init__.py
music_riff/cant_use_.py
music_riff/fix_bug_.py
music_riff/sandbox1_.py
music_riff/utils_.py
package_name/__init__.py
package_name/cant_use_.py
package_name/fix_bug_.py
package_name/sandbox1_.py
package_name/utils_.py
riff_music/__init__.py
riff_music/cant_use_.py
riff_music/fix_bug_.py
riff_music/sandbox1_.py
riff_music/utils_riff.py
riff_music-0.1.0rc2.dist-info/LICENSE
riff_music-0.1.0rc2.dist-info/METADATA
riff_music-0.1.0rc2.dist-info/WHEEL
riff_music-0.1.0rc2.dist-info/top_level.txt
riff_music-0.1.0rc2.dist-info/RECORD
