Metadata-Version: 2.1
Name: riff-music
Version: 0.1.0rc2
Summary: <add short describtion here>
Author: Dear Norathee
License: MIT
License-File: LICENSE
Requires-Dist: pandas
Requires-Dist: os-toolkit >=0.1.1
Requires-Dist: py-string-tool >=0.1.3
Requires-Dist: python-wizard >=0.1.1
